pyrvea/EAs/NSGAIII.py
pyrvea/EAs/RVEA.py
pyrvea/EAs/__init__.py
pyrvea/EAs/baseEA.py
pyrvea/OtherTools/IsNotebook.py
pyrvea/OtherTools/ReferenceVectors.py
pyrvea/OtherTools/__init__.py
pyrvea/OtherTools/newRV.py
pyrvea/OtherTools/plotlyanimate.py
pyrvea/OtherTools/symmetric_vectors.py
pyrvea/Population/Population.py
pyrvea/Population/__init__.py
pyrvea/Problem/__init__.py
pyrvea/Problem/baseProblem.py
pyrvea/Problem/testProblem.py
pyrvea/Recombination/__init__.py
pyrvea/Selection/APD_select.py
pyrvea/Selection/NSGAIII_select.py
pyrvea/Selection/__init__.py
pyrvea/__init__.py
pyrvea-0.1.1.dist-info/LICENSE
pyrvea-0.1.1.dist-info/WHEEL
pyrvea-0.1.1.dist-info/METADATA
pyrvea-0.1.1.dist-info/RECORD
